trytond/modules/calendar/__init__.py
trytond/modules/calendar/calendar.xml
trytond/modules/calendar/calendar_.py
trytond/modules/calendar/configuration.py
trytond/modules/calendar/configuration.xml
trytond/modules/calendar/exceptions.py
trytond/modules/calendar/ir.py
trytond/modules/calendar/message.xml
trytond/modules/calendar/tryton.cfg
trytond/modules/calendar/locale/ca.po
trytond/modules/calendar/locale/de.po
trytond/modules/calendar/locale/es.po
trytond/modules/calendar/locale/fr.po
trytond/modules/calendar/locale/it.po
trytond/modules/calendar/tests/__init__.py
trytond/modules/calendar/tests/scenario_calendar.py
trytond/modules/calendar/tests/scenario_calendar.rst
trytond/modules/calendar/tests/test_module.py
trytond/modules/calendar/tests/test_scenario.py
trytond/modules/calendar/view/attendee_form.xml
trytond/modules/calendar/view/attendee_tree.xml
trytond/modules/calendar/view/calendar_form.xml
trytond/modules/calendar/view/calendar_model_form.xml
trytond/modules/calendar/view/calendar_model_tree.xml
trytond/modules/calendar/view/calendar_tree.xml
trytond/modules/calendar/view/category_form.xml
trytond/modules/calendar/view/category_tree.xml
trytond/modules/calendar/view/event_calendar.xml
trytond/modules/calendar/view/event_form.xml
trytond/modules/calendar/view/event_tree.xml
trytond/modules/calendar/view/event_tree_occurence.xml
trytond/modules/calendar/view/exdate_form.xml
trytond/modules/calendar/view/exdate_tree.xml
trytond/modules/calendar/view/exrule_form.xml
trytond/modules/calendar/view/exrule_tree.xml
trytond/modules/calendar/view/location_form.xml
trytond/modules/calendar/view/location_tree.xml
trytond/modules/calendar/view/rdate_form.xml
trytond/modules/calendar/view/rdate_tree.xml
trytond/modules/calendar/view/resource_form.xml
trytond/modules/calendar/view/resource_tree.xml
trytond/modules/calendar/view/rrule_form.xml
trytond/modules/calendar/view/rrule_tree.xml
m9s_calendar-7.0.0.dist-info/LICENSE
m9s_calendar-7.0.0.dist-info/METADATA
m9s_calendar-7.0.0.dist-info/WHEEL
m9s_calendar-7.0.0.dist-info/entry_points.txt
m9s_calendar-7.0.0.dist-info/top_level.txt
m9s_calendar-7.0.0.dist-info/RECORD
